acas_auth/__init__.py
acas_auth/application/__init__.py
acas_auth/application/extensions/__init__.py
acas_auth/application/user/__init__.py
acas_auth/application/user/forms.py
acas_auth/application/user/models.py
acas_auth/application/user/views.py
acas_auth-2.0.4.dist-info/METADATA
acas_auth-2.0.4.dist-info/WHEEL
acas_auth-2.0.4.dist-info/top_level.txt
acas_auth-2.0.4.dist-info/RECORD
