Metadata-Version: 2.1
Name: acas-auth
Version: 2.0.4
Requires-Dist: Flask ==3.0.0
Requires-Dist: Flask-Bcrypt ==1.0.1
Requires-Dist: Flask-Login ==0.6.3
Requires-Dist: Flask-Mail ==0.9.1
Requires-Dist: Flask-Migrate ==4.0.5
